EasyNN/__init__.py
EasyNN/_abc.py
EasyNN/abc.py
EasyNN/typing.py
EasyNN/batch/__init__.py
EasyNN/batch/abc.py
EasyNN/batch/mini.py
EasyNN/callbacks/__init__.py
EasyNN/callbacks/abc.py
EasyNN/callbacks/print.py
EasyNN/callbacks/plot/__init__.py
EasyNN/callbacks/plot/abc.py
EasyNN/callbacks/plot/training_accuracy.py
EasyNN/callbacks/plot/training_loss.py
EasyNN/callbacks/plot/validation_accuracy.py
EasyNN/callbacks/plot/validation_loss.py
EasyNN/callbacks/termination/__init__.py
EasyNN/callbacks/termination/reach_accuracy.py
EasyNN/classifier/__init__.py
EasyNN/classifier/classifier.py
EasyNN/dataset/__init__.py
EasyNN/examples/__init__.py
EasyNN/examples/cifar10/__init__.py
EasyNN/examples/cifar10/data.py
EasyNN/examples/cifar10/structure.py
EasyNN/examples/cifar10/trained.py
EasyNN/examples/cifar10/untrained.py
EasyNN/examples/mnist/__init__.py
EasyNN/examples/mnist/fashion/__init__.py
EasyNN/examples/mnist/fashion/data.py
EasyNN/examples/mnist/fashion/structure.py
EasyNN/examples/mnist/fashion/trained.py
EasyNN/examples/mnist/fashion/untrained.py
EasyNN/examples/mnist/number/__init__.py
EasyNN/examples/mnist/number/data.py
EasyNN/examples/mnist/number/structure.py
EasyNN/examples/mnist/number/trained.py
EasyNN/examples/mnist/number/untrained.py
EasyNN/loss/__init__.py
EasyNN/loss/abc.py
EasyNN/loss/log_likelihood.py
EasyNN/loss/mean_square_error.py
EasyNN/loss/negative_likelihood.py
EasyNN/model/__init__.py
EasyNN/model/abc.py
EasyNN/model/bias.py
EasyNN/model/dense_layer.py
EasyNN/model/network.py
EasyNN/model/normalize.py
EasyNN/model/randomize.py
EasyNN/model/weight.py
EasyNN/model/activation/__init__.py
EasyNN/model/activation/abc.py
EasyNN/model/activation/log_softmax.py
EasyNN/model/activation/relu.py
EasyNN/model/activation/softmax.py
EasyNN/optimizer/__init__.py
EasyNN/optimizer/abc.py
EasyNN/optimizer/adam.py
EasyNN/optimizer/gradient_descent.py
EasyNN/optimizer/momentum_descent.py
EasyNN/optimizer/nesterov.py
EasyNN/utilities/__init__.py
EasyNN-0.2.2.dist-info/LICENSE.txt
EasyNN-0.2.2.dist-info/METADATA
EasyNN-0.2.2.dist-info/WHEEL
EasyNN-0.2.2.dist-info/top_level.txt
EasyNN-0.2.2.dist-info/RECORD
