Metadata-Version: 2.1
Name: EasyNN
Version: 0.2.2
Summary: EasyNN is a python package designed to provide an easy-to-use neural network. The package is designed to work right out of the box, while also allowing the user to customize features as they see fit.
Author: Jack Nguyen
Author-email: Daniel Wilczak <danielwilczak101@gmail.com>
License: mit
Project-URL: repository, https://github.com/danielwilczak101/EasyNN
Keywords: artificial intelligence,machine learning,neural networks
Classifier: License :: OSI Approved :: GNU General Public License v2 or later (GPLv2+)
Classifier: Operating System :: OS Independent
Classifier: Programming Language :: Python :: 3.6
Classifier: Programming Language :: Python :: 3.7
Classifier: Programming Language :: Python :: 3.8
Classifier: Programming Language :: Python :: 3.9
Classifier: Programming Language :: Python :: 3.10
Classifier: Topic :: Scientific/Engineering :: Artificial Intelligence
Requires-Python: >=3.7
License-File: LICENSE.txt
Requires-Dist: matplotlib (~=3.3.2)
Requires-Dist: clint (>=0.5.1)
Requires-Dist: tabulate (>=0.8.7)
Requires-Dist: requests (>=2.26.0)
Requires-Dist: numpy (>=1.21.3)
Requires-Dist: nptyping (>=2.0.0)
Requires-Dist: beautifulsoup4 (==4.11.1)
Requires-Dist: google-search-results (==2.4.1)
Requires-Dist: prettyformatter (==1.1.1)
